src/IP/Control_axi_interface.v
`default_nettype none
// `timescale 1ns / 1ps

module Control_axi_interface
  #(parameter integer ADDR_WIDTH = 12,
    parameter integer DATA_WIDTH = 32)
   (// system signals
    input wire                    ACLK,
    input wire                    ARESET,
    input wire                    ACLK_EN,

    // write address channel
    input wire                    AWVALID,
    output wire                   AWREADY,
    input wire [ADDR_WIDTH-1:0]   AWADDR,

    // write data channel
    input wire                    WVALID,
    output wire                   WREADY,
    input wire [DATA_WIDTH-1:0]   WDATA,
    input wire [DATA_WIDTH/8-1:0] WSTRB,

    // write response channel
    output wire                   BVALID,
    input wire                    BREADY,
    output wire [2-1:0]           BRESP,

    // read address channel
    input wire                    ARVALID,
    output wire                   ARREADY,
    input wire [ADDR_WIDTH-1:0]   ARADDR,

    // read data channel
    output wire                   RVALID,
    input wire                    RREADY,
    output wire [DATA_WIDTH-1:0]  RDATA,
    output wire [2-1:0]           RRESP,

    // control signals
    output wire                   interrupt,
    output wire                   ap_start,
    input wire                    ap_done,

    // kernel arguments
    output wire [31:0]            scalar00,
    output wire [63:0]            A
    // end
    );

   //------------------------Address Info-------------------
   // 0x00 : Control signals
   //        bit 0  - ap_start (Read/Write/COH)
   //        bit 1  - ap_done (Read/COR)
   //        bit 2  - ap_idle (Read)
   //        others - reserved
   // 0x04 : Global Interrupt Enable Register
   //        bit 0  - Global Interrupt Enable (Read/Write)
   //        others - reserved
   // 0x08 : IP Interrupt Enable Register (Read/Write)
   //        bit 0  - Channel 0 (ap_done)
   //        bit 1  - Channel 1 (ap_ready)
   //        others - reserved
   // 0x0c : IP Interrupt Status Register (Read/TOW)
   //        bit 0  - Channel 0 (ap_done)
   //        bit 1  - Channel 1 (ap_ready)
   //        others - reserved
   // 0x10 : Data signal of scalar00
   //        bit 31~0 - scalar00[31:0] (Read/Write)
   // 0x14 : reserved
   // 0x18 : Address of A, bits [31:0]
   // 0x1c : Address of A, bits [63:32]
   // (SC = Self Clear, COR = Clear on Read, TOW = Toggle on Write, COH = Clear on Handshake)

   //------------------------Parameters----------------------
   localparam
     ADDR_AP_CTRL         = 6'h00, // defines application control interface
     ADDR_GIE             = 6'h04, // global interrupt enable register
     ADDR_IER             = 6'h08, // IP interrupt enable register
     ADDR_ISR             = 6'h0c, // interrupt status register
     ADDR_SCALAR00_DATA_0 = 6'h10, // data signal of scalar00[31:0] (read/write)
     ADDR_SCALAR00_CTRL   = 6'h14, // control signal
     ADDR_A_0             = 6'h18, // address of A
     ADDR_A_1             = 6'h1c,

     // write fsm states
     WRIDLE               = 2'd0,
     WRDATA               = 2'd1,
     WRRESP               = 2'd2,
     WRRESET              = 2'd3,

     // read fsm states
     RDIDLE               = 2'd0,
     RDDATA               = 2'd1,
     RDRESET              = 2'd2,

     ADDR_BITS            = 6;

   //------------------------Local signal-------------------
   reg [1:0]                            wstate = WRRESET; // write fsm state
   reg [1:0]                            wnext; // next state for write fsm
   reg [ADDR_BITS-1:0]                  waddr; // write address
   wire [31:0]                          wmask; // valid bits for write data

   wire                                 aw_hs; // address write hand shake
   wire                                 w_hs; // write hand shake

   reg [1:0]                            rstate = RDRESET; // read fsm state
   reg [1:0]                            rnext; // next fsm state for read fsm
   reg [31:0]                           rdata; // read data
   wire [ADDR_BITS-1:0]                 raddr; // read address
   wire                                 ar_hs; // address read hand shake

   // internal registers
   reg                                  int_ap_start = 1'b0;
   reg                                  int_ap_done = 1'b0;
   reg                                  int_gie = 1'b0;
   reg [1:0]                            int_ier = 2'b0;
   reg [1:0]                            int_isr = 2'b0;
   // generated
   reg [31:0]                           int_scalar00 = 32'b0;
   reg [63:0]                           int_A = 'd0;

   //------------------------AXI write fsm------------------
   assign AWREADY = (wstate == WRIDLE); // ready to receive addresses when write fsm is idle
   assign WREADY = (wstate == WRDATA); // ready to get data in write fsm state 2
   assign BRESP = 2'b00; // keep this low (???)
   assign BVALID = (wstate == WRRESP); // done performing write, respond on response channel
   // write strobing nonsense (see if I can remove this)
   assign wmask   = { {8{WSTRB[3]}}, {8{WSTRB[2]}}, {8{WSTRB[1]}}, {8{WSTRB[0]}} };
   assign aw_hs = AWVALID & AWREADY; // write address can be performed when valid and ready are high for that channel
   assign w_hs = WVALID & WREADY;

   // wstate (transition fsm to wnext)
   always @(posedge ACLK) begin
      if (ARESET)
        wstate <= WRRESET;
      else if (ACLK_EN)
        wstate <= wnext;
   end

   // wnext
   always @(*) begin
      case (wstate)
        WRIDLE:
          if (AWVALID)
            wnext = WRDATA;
          else
            wnext = WRIDLE;
        WRDATA:
          if (WVALID)
            wnext = WRRESP;
          else
            wnext = WRDATA;
        WRRESP:
          if (BREADY)
            wnext = WRIDLE;
          else
            wnext = WRRESP;
        default:
          wnext = WRIDLE;
      endcase
   end

   // waddr
   always @(posedge ACLK) begin
      if (ARESET)
        waddr <= 'b0;
      else if (ACLK_EN) begin
         if (aw_hs)
           waddr <= AWADDR[ADDR_BITS-1:0];
      end
   end

   //------------------------AXI read fsm-------------------
   assign ARREADY = (rstate == RDIDLE); // addr ready when read fsm is idle
   assign RVALID = (rstate == RDDATA); // valid when in read data state

   assign raddr = ARADDR[ADDR_BITS-1:0];
   assign RDATA = rdata; // output data
   assign RRESP = 2'b00; // OKAY

   assign ar_hs = ARVALID & ARREADY;

   // rstate
   always @(posedge ACLK) begin
      if (ARESET)
        rstate <= RDRESET;
      else if (ACLK_EN)
        rstate <= rnext;
   end

   // rnext
   always @(*) begin
      case (rstate)
        RDIDLE:
           if (ARVALID)
             rnext = RDDATA;
           else
             rnext = RDIDLE;
        RDDATA:
          if (RREADY & RVALID) // can't I just look at ready here?
            rnext = RDIDLE;
          else
            rnext = RDDATA;
        default:
          rnext = RDIDLE;
      endcase
   end

   // rdata
   always @(posedge ACLK) begin
      if (ACLK_EN) begin
         if (ar_hs) begin
            rdata <= 32'd0;
            case (raddr)
              ADDR_AP_CTRL: begin
                 rdata[0] <= int_ap_start;
                 rdata[1] <= int_ap_done;
              end
              ADDR_GIE: begin
                 rdata <= {{31{1'b0}}, int_gie};
              end
              ADDR_IER: begin
                 rdata <= {{30{1'b0}}, int_ier};
              end
              ADDR_ISR: begin
                 rdata <= {{30{1'b0}}, int_isr};
              end
              ADDR_SCALAR00_DATA_0: begin
                 rdata <= int_scalar00[31:0];
              end
              ADDR_A_0: begin
                 rdata <= int_A[31:0];
              end
              ADDR_A_1: begin
                 rdata <= int_A[63:32];
              end
              default: begin
                 rdata <= 32'd0;
              end
            endcase
         end
      end
   end

   //------------------------Register logic-----------------
   assign interrupt = int_gie & (|int_isr);
   assign ap_start = int_ap_start;
   assign scalar00 = int_scalar00;
   assign A = int_A;

   // int_ap_start
   always @(posedge ACLK) begin
      if (ARESET)
        int_ap_start <= 1'b0;
      else if (ACLK_EN) begin
         if (w_hs && waddr == ADDR_AP_CTRL && WDATA[0] && WSTRB[0])
           int_ap_start <= 1'b1;
         else if (ap_done)
           int_ap_start <= 1'b0; // clear on handshake
      end
   end

   // int_ap_done
   always @(posedge ACLK) begin
      if (ARESET)
        int_ap_done <= 1'b0;
      else if (ACLK_EN) begin
         if (ap_done)
           int_ap_done <= 1'b1;
         else if (ar_hs && raddr == ADDR_AP_CTRL)
           int_ap_done <= 1'b0; // clear on read
      end
   end

   // int_gie
   always @(posedge ACLK) begin
      if (ARESET)
        int_gie <= 1'b0;
      else if (ACLK_EN) begin
         if (w_hs && waddr == ADDR_GIE && WSTRB[0])
           int_gie <= WDATA[0];
      end
   end

   // int_ier
   always @(posedge ACLK) begin
      if (ARESET)
        int_ier[0] <= 1'b0;
      else if (ACLK_EN) begin
         if (w_hs && waddr == ADDR_IER && WSTRB[0])
           int_ier <= WDATA[1:0];
      end
   end

   // int_isr[0]
   always @(posedge ACLK) begin
      if (ARESET)
        int_isr[0] <= 1'b0;
      else if (ACLK_EN) begin
         if (int_ier[0] & ap_done)
           int_isr[0] <= 1'b1;
         else if (w_hs && waddr == ADDR_ISR && WSTRB[0])
           int_isr[0] <= int_isr[0] ^ WDATA[0]; // toggle on write
      end
   end

   // int_isr[1]
   always @(posedge ACLK) begin
      if (ARESET)
        int_isr[1] <= 1'b0;
      else if (ACLK_EN) begin
         if (int_ier[1] & ap_done)
           int_isr[1] <= 1'b1;
         else if (w_hs && waddr == ADDR_ISR && WSTRB[0])
           int_isr[1] <= int_isr[1] ^ WDATA[1]; // toggle on write
      end
   end

   // int_scalar00
   always @(posedge ACLK) begin
      if (ARESET)
        int_scalar00[31:0] <= 'd0;
      else if (ACLK_EN) begin
         if (w_hs && waddr == ADDR_SCALAR00_DATA_0)
           int_scalar00[31:0] <= (WDATA[31:0] & wmask) | (int_scalar00[31:0] & ~wmask);
      end
   end

   // int_A[31:0]
   always @(posedge ACLK) begin
      if (ARESET)
        int_A[31:0] <= 0;
      else if (ACLK_EN) begin
         if (w_hs && waddr == ADDR_A_0)
           int_A[31:0] <= (WDATA[31:0] & wmask) | (int_A[31:0] & ~wmask);
      end
   end

   // int_A[63:32]
   always @(posedge ACLK) begin
      if (ARESET)
        int_A[31:0] <= 0;
      else begin
         if (w_hs && waddr == ADDR_A_1)
           int_A[63:32] <= (WDATA[31:0] & wmask) | (int_A[63:32] & ~wmask);
      end
   end

endmodule

`default_nettype wire

src/IP/top_level.v
`default_nettype none
// `timescale 1ns / 1ps

module Toplevel
  #(parameter integer C_S_AXI_ADDR_WIDTH = 12,
    parameter integer C_S_AXI_DATA_WIDTH = 32,
    parameter integer M00_AXI_ADDR_WIDTH = 64,
    parameter integer M00_AXI_DATA_WIDTH = 32 /* original 512 */)
   (
    // system signals
    input wire                             ap_clk,
    output wire                            ap_interrupt,

    //////////// AXI4-lite slave interface //////////////
    //////////// this is the thing that let's us be
    //////////// called from software
    // write address channel
    input wire                             s_axi_control_awvalid,
    output wire                            s_axi_control_awready,
    input wire [C_S_AXI_ADDR_WIDTH-1:0]    s_axi_control_awaddr,

    // write data channel
    input wire                             s_axi_control_wvalid,
    output wire                            s_axi_control_wready,
    input wire [C_S_AXI_DATA_WIDTH-1:0]    s_axi_control_wdata,
    input wire [C_S_AXI_DATA_WIDTH/8-1:0]  s_axi_control_wstrb, // ?? is this needed

    // write response channel
    output wire                            s_axi_control_bvalid,
    input wire                             s_axi_control_bready,
    output wire [2-1:0]                    s_axi_control_bresp,

    // read address channel
    input wire                             s_axi_control_arvalid,
    output wire                            s_axi_control_arready,
    input wire [C_S_AXI_ADDR_WIDTH-1:0]    s_axi_control_araddr,

    // read data channel
    output wire                            s_axi_control_rvalid,
    input wire                             s_axi_control_rready,
    output wire [C_S_AXI_DATA_WIDTH-1:0]   s_axi_control_rdata,
    output wire [2-1:0]                    s_axi_control_rresp,

    //////////// AXI4-lite master interface //////////////
   // write address channel
    output wire                            m00_axi_awvalid,
    input wire                             m00_axi_awready,
    output wire [M00_AXI_ADDR_WIDTH-1:0]   m00_axi_awaddr,
    output wire [8-1:0]                    m00_axi_awlen,

    // write data channel
    output wire                            m00_axi_wvalid,
    input wire                             m00_axi_wready,
    output wire [M00_AXI_DATA_WIDTH-1:0]   m00_axi_wdata,
    output wire [M00_AXI_DATA_WIDTH/8-1:0] m00_axi_wstrb,
    output wire                            m00_axi_wlast,

    // write response channel
    input wire                             m00_axi_bvalid,
    output wire                            m00_axi_bready,

    // read address channel
    output wire                            m00_axi_arvalid,
    input wire                             m00_axi_arready,
    output wire [M00_AXI_ADDR_WIDTH-1:0]   m00_axi_araddr,
    output wire [8-1:0]                    m00_axi_arlen,

    // read data channel
    input wire                             m00_axi_rvalid,
    output wire                            m00_axi_rready,
    input wire [M00_AXI_DATA_WIDTH-1:0]    m00_axi_rdata,
    input wire                             m00_axi_rlast

    // end
    );

   localparam ARESET = 1'b0;
   localparam ACLK_EN = 1'b1;

   wire                                    ap_start;
   wire                                    ap_done;
   wire [31:0]                             scalar00;
   wire [63:0]                             A;

   // AXI4-Lite slave control interface
   Control_axi_interface
     #(.ADDR_WIDTH (C_S_AXI_ADDR_WIDTH),
       .DATA_WIDTH (C_S_AXI_DATA_WIDTH))
   inst_control_axi
     (.ACLK(ap_clk),
      .ARESET(ARESET),
      .ACLK_EN(ACLK_EN),
      .AWVALID(s_axi_control_awvalid),
      .AWREADY(s_axi_control_awready),
      .AWADDR(s_axi_control_awaddr),
      .WVALID(s_axi_control_wvalid),
      .WREADY(s_axi_control_wready),
      .WDATA(s_axi_control_wdata),
      .WSTRB(s_axi_control_wstrb),
      .BVALID(s_axi_control_bvalid),
      .BREADY(s_axi_control_bready),
      .BRESP(s_axi_control_bresp),
      .ARVALID(s_axi_control_arvalid),
      .ARREADY(s_axi_control_arready),
      .ARADDR(s_axi_control_araddr),
      .RVALID(s_axi_control_rvalid),
      .RREADY(s_axi_control_rready),
      .RDATA(s_axi_control_rdata),
      .RRESP(s_axi_control_rresp),
      .interrupt(ap_interrupt),
      .ap_start(ap_start),
      .ap_done(ap_done),
      .scalar00(scalar00),
      .A(A));

   //------------------------Application logic-----------------
   assign ap_done = (ap_start && (A_wr_data == scalar00 | counter == (scalar00 << 4)));
   reg [31:0]                              counter;
   always @(posedge ap_clk) begin
      if (ARESET)
        counter <= 32'd0;
      else begin
         if (ap_start)
           counter <= counter + 32'd1;
         else
           counter <= counter;
      end
   end

   //------------------------write to A-----------------
   localparam A_WR_RESET = 4'd0;
   localparam A_WR_IDLE = 4'd1;
   localparam A_WR_DATA = 4'd2;
   localparam A_WR_RESP = 4'd3;

   reg [3:0] A_wr_state = A_WR_RESET;
   reg [3:0] A_wr_next = 'b0;
   reg [M00_AXI_DATA_WIDTH-1:0] A_wr_data = 'b0;
   reg [7:0] A_wr_addr = 'b0;

   always @(posedge ap_clk) begin
      if (ARESET)
        A_wr_state <= A_WR_RESET;
      else if (ap_start)
        A_wr_state <= A_wr_next;
      else
        A_wr_state <= A_wr_state;
   end

   always @(*) begin
      case (A_wr_state)
        A_WR_IDLE:
           if (m00_axi_awready)
             A_wr_next = A_WR_DATA;
           else
             A_wr_next = A_WR_IDLE;
        A_WR_DATA:
           if (m00_axi_wready)
             A_wr_next = A_WR_RESP;
           else
             A_wr_next = A_WR_DATA;
        A_WR_RESP:
          if (m00_axi_bvalid)
            A_wr_next = A_WR_IDLE;
          else
            A_wr_next = A_WR_RESP;
        default:
          A_wr_next = A_WR_IDLE;
      endcase
   end

   always @(posedge ap_clk) begin
      if (ARESET)
        A_wr_addr <= 'b0;
      else if (A_wr_state == A_WR_RESP)
        A_wr_addr <= A_wr_addr + 1;
      else
        A_wr_addr <= A_wr_addr;
   end

   // write address channel
   assign m00_axi_awvalid = (A_wr_state == A_WR_IDLE);
   assign m00_axi_awaddr = A + ({{56{1'b0}}, A_wr_addr} << 2);
   assign m00_axi_awlen = 'b0;

   assign m00_axi_wvalid = (A_wr_state == A_WR_DATA);
   assign m00_axi_wdata = {{24{1'b0}}, A_wr_addr};
   assign m00_axi_wstrb = {M00_AXI_DATA_WIDTH/8{1'd1}};
   assign m00_axi_wlast = 'b1;

   assign m00_axi_bready = (A_wr_state == A_WR_RESP);

   // we're not doing any reading so keep these low
   assign m00_axi_arvalid = 'b0;
   assign m00_axi_araddr = 'b0;
   assign m00_axi_arlen = 'b0;
   assign m00_axi_rready = 'b0;

endmodule
`default_nettype wire

test.vcd
$version Generated by VerilatedVcd $end
$date Wed Apr 21 12:05:33 2021
 $end
$timescale 1ps $end

 $scope module TOP $end
  $var wire  1 8 ap_clk $end
  $var wire  1 9 ap_interrupt $end
  $var wire 64 Y m00_axi_araddr [63:0] $end
  $var wire  8 [ m00_axi_arlen [7:0] $end
  $var wire  1 X m00_axi_arready $end
  $var wire  1 W m00_axi_arvalid $end
  $var wire 64 M m00_axi_awaddr [63:0] $end
  $var wire  8 O m00_axi_awlen [7:0] $end
  $var wire  1 L m00_axi_awready $end
  $var wire  1 K m00_axi_awvalid $end
  $var wire  1 V m00_axi_bready $end
  $var wire  1 U m00_axi_bvalid $end
  $var wire 32 ^ m00_axi_rdata [31:0] $end
  $var wire  1 _ m00_axi_rlast $end
  $var wire  1 ] m00_axi_rready $end
  $var wire  1 \ m00_axi_rvalid $end
  $var wire 32 R m00_axi_wdata [31:0] $end
  $var wire  1 T m00_axi_wlast $end
  $var wire  1 Q m00_axi_wready $end
  $var wire  4 S m00_axi_wstrb [3:0] $end
  $var wire  1 P m00_axi_wvalid $end
  $var wire 12 F s_axi_control_araddr [11:0] $end
  $var wire  1 E s_axi_control_arready $end
  $var wire  1 D s_axi_control_arvalid $end
  $var wire 12 < s_axi_control_awaddr [11:0] $end
  $var wire  1 ; s_axi_control_awready $end
  $var wire  1 : s_axi_control_awvalid $end
  $var wire  1 B s_axi_control_bready $end
  $var wire  2 C s_axi_control_bresp [1:0] $end
  $var wire  1 A s_axi_control_bvalid $end
  $var wire 32 I s_axi_control_rdata [31:0] $end
  $var wire  1 H s_axi_control_rready $end
  $var wire  2 J s_axi_control_rresp [1:0] $end
  $var wire  1 G s_axi_control_rvalid $end
  $var wire 32 ? s_axi_control_wdata [31:0] $end
  $var wire  1 > s_axi_control_wready $end
  $var wire  4 @ s_axi_control_wstrb [3:0] $end
  $var wire  1 = s_axi_control_wvalid $end
  $scope module Toplevel $end
   $var wire 64 & A [63:0] $end
   $var wire  1 g ACLK_EN [0:0] $end
   $var wire  1 f ARESET [0:0] $end
   $var wire  4 j A_WR_DATA [3:0] $end
   $var wire  4 i A_WR_IDLE [3:0] $end
   $var wire  4 h A_WR_RESET [3:0] $end
   $var wire  4 k A_WR_RESP [3:0] $end
   $var wire  8 * A_wr_addr [7:0] $end
   $var wire 32 l A_wr_data [31:0] $end
   $var wire  4 3 A_wr_next [3:0] $end
   $var wire  4 ) A_wr_state [3:0] $end
   $var wire 32 c C_S_AXI_ADDR_WIDTH [31:0] $end
   $var wire 32 d C_S_AXI_DATA_WIDTH [31:0] $end
   $var wire 32 e M00_AXI_ADDR_WIDTH [31:0] $end
   $var wire 32 d M00_AXI_DATA_WIDTH [31:0] $end
   $var wire  1 8 ap_clk $end
   $var wire  1 $ ap_done $end
   $var wire  1 9 ap_interrupt $end
   $var wire  1 # ap_start $end
   $var wire 32 ( counter [31:0] $end
   $var wire 64 Y m00_axi_araddr [63:0] $end
   $var wire  8 [ m00_axi_arlen [7:0] $end
   $var wire  1 X m00_axi_arready $end
   $var wire  1 W m00_axi_arvalid $end
   $var wire 64 M m00_axi_awaddr [63:0] $end
   $var wire  8 O m00_axi_awlen [7:0] $end
   $var wire  1 L m00_axi_awready $end
   $var wire  1 K m00_axi_awvalid $end
   $var wire  1 V m00_axi_bready $end
   $var wire  1 U m00_axi_bvalid $end
   $var wire 32 ^ m00_axi_rdata [31:0] $end
   $var wire  1 _ m00_axi_rlast $end
   $var wire  1 ] m00_axi_rready $end
   $var wire  1 \ m00_axi_rvalid $end
   $var wire 32 R m00_axi_wdata [31:0] $end
   $var wire  1 T m00_axi_wlast $end
   $var wire  1 Q m00_axi_wready $end
   $var wire  4 S m00_axi_wstrb [3:0] $end
   $var wire  1 P m00_axi_wvalid $end
   $var wire 12 F s_axi_control_araddr [11:0] $end
   $var wire  1 E s_axi_control_arready $end
   $var wire  1 D s_axi_control_arvalid $end
   $var wire 12 < s_axi_control_awaddr [11:0] $end
   $var wire  1 ; s_axi_control_awready $end
   $var wire  1 : s_axi_control_awvalid $end
   $var wire  1 B s_axi_control_bready $end
   $var wire  2 C s_axi_control_bresp [1:0] $end
   $var wire  1 A s_axi_control_bvalid $end
   $var wire 32 I s_axi_control_rdata [31:0] $end
   $var wire  1 H s_axi_control_rready $end
   $var wire  2 J s_axi_control_rresp [1:0] $end
   $var wire  1 G s_axi_control_rvalid $end
   $var wire 32 ? s_axi_control_wdata [31:0] $end
   $var wire  1 > s_axi_control_wready $end
   $var wire  4 @ s_axi_control_wstrb [3:0] $end
   $var wire  1 = s_axi_control_wvalid $end
   $var wire 32 % scalar00 [31:0] $end
   $scope module inst_control_axi $end
    $var wire 64 & A [63:0] $end
    $var wire  1 8 ACLK $end
    $var wire  1 g ACLK_EN $end
    $var wire  6 m ADDR_AP_CTRL [5:0] $end
    $var wire  6 s ADDR_A_0 [5:0] $end
    $var wire  6 t ADDR_A_1 [5:0] $end
    $var wire 32 y ADDR_BITS [31:0] $end
    $var wire  6 n ADDR_GIE [5:0] $end
    $var wire  6 o ADDR_IER [5:0] $end
    $var wire  6 p ADDR_ISR [5:0] $end
    $var wire  6 r ADDR_SCALAR00_CTRL [5:0] $end
    $var wire  6 q ADDR_SCALAR00_DATA_0 [5:0] $end
    $var wire 32 c ADDR_WIDTH [31:0] $end
    $var wire 12 F ARADDR [11:0] $end
    $var wire  1 f ARESET $end
    $var wire  1 E ARREADY $end
    $var wire  1 D ARVALID $end
    $var wire 12 < AWADDR [11:0] $end
    $var wire  1 ; AWREADY $end
    $var wire  1 : AWVALID $end
    $var wire  1 B BREADY $end
    $var wire  2 C BRESP [1:0] $end
    $var wire  1 A BVALID $end
    $var wire 32 d DATA_WIDTH [31:0] $end
    $var wire 32 I RDATA [31:0] $end
    $var wire  2 v RDDATA [1:0] $end
    $var wire  2 u RDIDLE [1:0] $end
    $var wire  2 w RDRESET [1:0] $end
    $var wire  1 H RREADY $end
    $var wire  2 J RRESP [1:0] $end
    $var wire  1 G RVALID $end
    $var wire 32 ? WDATA [31:0] $end
    $var wire  2 v WRDATA [1:0] $end
    $var wire  1 > WREADY $end
    $var wire  2 u WRIDLE [1:0] $end
    $var wire  2 x WRRESET [1:0] $end
    $var wire  2 w WRRESP [1:0] $end
    $var wire  4 @ WSTRB [3:0] $end
    $var wire  1 = WVALID $end
    $var wire  1 $ ap_done $end
    $var wire  1 # ap_start $end
    $var wire  1 7 ar_hs $end
    $var wire  1 ` aw_hs $end
    $var wire 64 & int_A [63:0] $end
    $var wire  1 / int_ap_done $end
    $var wire  1 # int_ap_start $end
    $var wire  1 0 int_gie $end
    $var wire  2 1 int_ier [1:0] $end
    $var wire  2 2 int_isr [1:0] $end
    $var wire 32 % int_scalar00 [31:0] $end
    $var wire  1 9 interrupt $end
    $var wire  6 b raddr [5:0] $end
    $var wire 32 . rdata [31:0] $end
    $var wire  2 a rnext [1:0] $end
    $var wire  2 - rstate [1:0] $end
    $var wire 32 % scalar00 [31:0] $end
    $var wire  1 6 w_hs $end
    $var wire  6 , waddr [5:0] $end
    $var wire 32 5 wmask [31:0] $end
    $var wire  2 4 wnext [1:0] $end
    $var wire  2 + wstate [1:0] $end
   $upscope $end
  $upscope $end
 $upscope $end
$enddefinitions $end


#0
0#
0$
b00000000000000000000000000000000 %
b0000000000000000000000000000000000000000000000000000000000000000 &
b00000000000000000000000000000000 (
b0000 )
b00000000 *
b11 +
b000000 ,
b10 -
b00000000000000000000000000000000 .
0/
00
b00 1
b00 2
b0001 3
b00 4
b00000000000000000000000000000000 5
06
07
08
09
1:
0;
b000000010000 <
1=
0>
b00000000000000000000000000011110 ?
b1111 @
0A
1B
b00 C
0D
0E
b000000000000 F
0G
1H
b00000000000000000000000000000000 I
b00 J
0K
0L
b0000000000000000000000000000000000000000000000000000000000000000 M
b00000000 O
0P
0Q
b00000000000000000000000000000000 R
b1111 S
1T
0U
0V
0W
0X
b0000000000000000000000000000000000000000000000000000000000000000 Y
b00000000 [
0\
0]
b00000000000000000000000000000000 ^
0_
0`
b00 a
b000000 b
b00000000000000000000000000001100 c
b00000000000000000000000000100000 d
b00000000000000000000000001000000 e
0f
1g
b0000 h
b0001 i
b0010 j
b0011 k
b00000000000000000000000000000000 l
b000000 m
b000100 n
b001000 o
b001100 p
b010000 q
b010100 r
b011000 s
b011100 t
b00 u
b01 v
b10 w
b11 x
b00000000000000000000000000000110 y
#1
b00 +
b00 -
b01 4
b11111111111111111111111111111111 5
18
1;
1E
1`
#2
08
#3
b01 +
b010000 ,
b10 4
16
18
0;
1>
0`
#4
08
#5
b00000000000000000000000000011110 %
b10 +
b00 4
06
18
0>
1A
#6
08
0:
0=
#7
b00 +
18
1;
0A
#8
08
1:
b000000000000 <
1=
b00000000000000000000000000000001 ?
1`
#9
b000000 ,
b01 4
18
#10
08
#11
b01 +
b10 4
16
18
0;
1>
0`
#12
08
#13
1#
b10 +
b00 4
06
18
0>
1A
#14
08
0:
0=
#15
b00000000000000000000000000000001 (
b0001 )
b00 +
18
1;
0A
1K
#16
08
#17
b00000000000000000000000000000010 (
18
#18
08
#19
b00000000000000000000000000000011 (
18
#20
08
#21
b00000000000000000000000000000100 (
18
#22
08
#23
b00000000000000000000000000000101 (
18
#24
08
#25
b00000000000000000000000000000110 (
18
#26
08
#27
b00000000000000000000000000000111 (
18
#28
08
#29
b00000000000000000000000000001000 (
18
#30
08
#31
b00000000000000000000000000001001 (
18
#32
08
#33
b00000000000000000000000000001010 (
18
#34
08
#35
b00000000000000000000000000001011 (
18
#36
08
#37
b00000000000000000000000000001100 (
18
#38
08
#39
b00000000000000000000000000001101 (
18
#40
08
1D
b01 a
#41
b00000000000000000000000000001110 (
17
18
#42
08
#43
b00000000000000000000000000001111 (
b01 -
b00000000000000000000000000000001 .
07
18
0E
1G
b00000000000000000000000000000001 I
b00 a
#44
08
0D
#45
b00000000000000000000000000010000 (
b00 -
18
1E
0G
#46
08
#47
b00000000000000000000000000010001 (
18
#48
08
#49
b00000000000000000000000000010010 (
18
#50
08
#51
b00000000000000000000000000010011 (
18
#52
08
#53
b00000000000000000000000000010100 (
18
#54
08
#55
b00000000000000000000000000010101 (
18
#56
08
#57
b00000000000000000000000000010110 (
18
#58
08
#59
b00000000000000000000000000010111 (
18
#60
08
#61
b00000000000000000000000000011000 (
18
#62
08
#63
b00000000000000000000000000011001 (
18
#64
08
#65
b00000000000000000000000000011010 (
18
#66
08
#67
b00000000000000000000000000011011 (
18
#68
08
#69
b00000000000000000000000000011100 (
18
#70
08
#71
b00000000000000000000000000011101 (
18
#72
08
#73
b00000000000000000000000000011110 (
18
#74
08
#75
b00000000000000000000000000011111 (
18
#76
08
#77
b00000000000000000000000000100000 (
18
#78
08
#79
b00000000000000000000000000100001 (
18
#80
08
1D
b01 a
#81
b00000000000000000000000000100010 (
17
18
#82
08
#83
b00000000000000000000000000100011 (
b01 -
07
18
0E
1G
b00 a
#84
08
0D
#85
b00000000000000000000000000100100 (
b00 -
18
1E
0G
#86
08
#87
b00000000000000000000000000100101 (
18
#88
08
#89
b00000000000000000000000000100110 (
18
#90
08
#91
b00000000000000000000000000100111 (
18
#92
08
#93
b00000000000000000000000000101000 (
18
#94
08
#95
b00000000000000000000000000101001 (
18
#96
08
#97
b00000000000000000000000000101010 (
18
#98
08
#99
b00000000000000000000000000101011 (
18
#100
08
#101
b00000000000000000000000000101100 (
18
#102
08
#103
b00000000000000000000000000101101 (
18
#104
08
#105
b00000000000000000000000000101110 (
18
#106
08
#107
b00000000000000000000000000101111 (
18
#108
08
#109
b00000000000000000000000000110000 (
18
#110
08
#111
b00000000000000000000000000110001 (
18
#112
08
#113
b00000000000000000000000000110010 (
18
#114
08
#115
b00000000000000000000000000110011 (
18
#116
08
#117
b00000000000000000000000000110100 (
18
#118
08
#119
b00000000000000000000000000110101 (
18
#120
08
1D
b01 a
#121
b00000000000000000000000000110110 (
17
18
#122
08
#123
b00000000000000000000000000110111 (
b01 -
07
18
0E
1G
b00 a
#124
08
0D
#125
b00000000000000000000000000111000 (
b00 -
18
1E
0G
#126
08
#127
b00000000000000000000000000111001 (
18
#128
08
#129
b00000000000000000000000000111010 (
18
#130
08
#131
b00000000000000000000000000111011 (
18
#132
08
#133
b00000000000000000000000000111100 (
18
#134
08
#135
b00000000000000000000000000111101 (
18
#136
08
#137
b00000000000000000000000000111110 (
18
#138
08
#139
b00000000000000000000000000111111 (
18
#140
08
#141
b00000000000000000000000001000000 (
18
#142
08
#143
b00000000000000000000000001000001 (
18
#144
08
#145
b00000000000000000000000001000010 (
18
#146
08
#147
b00000000000000000000000001000011 (
18
#148
08
#149
b00000000000000000000000001000100 (
18
#150
08
#151
b00000000000000000000000001000101 (
18
#152
08
#153
b00000000000000000000000001000110 (
18
#154
08
#155
b00000000000000000000000001000111 (
18
#156
08
#157
b00000000000000000000000001001000 (
18
#158
08
#159
b00000000000000000000000001001001 (
18
#160
08
1D
b01 a
#161
b00000000000000000000000001001010 (
17
18
#162
08
#163
b00000000000000000000000001001011 (
b01 -
07
18
0E
1G
b00 a
#164
08
0D
#165
b00000000000000000000000001001100 (
b00 -
18
1E
0G
#166
08
#167
b00000000000000000000000001001101 (
18
#168
08
#169
b00000000000000000000000001001110 (
18
#170
08
#171
b00000000000000000000000001001111 (
18
#172
08
#173
b00000000000000000000000001010000 (
18
#174
08
#175
b00000000000000000000000001010001 (
18
#176
08
#177
b00000000000000000000000001010010 (
18
#178
08
#179
b00000000000000000000000001010011 (
18
#180
08
#181
b00000000000000000000000001010100 (
18
#182
08
#183
b00000000000000000000000001010101 (
18
#184
08
#185
b00000000000000000000000001010110 (
18
#186
08
#187
b00000000000000000000000001010111 (
18
#188
08
#189
b00000000000000000000000001011000 (
18
#190
08
#191
b00000000000000000000000001011001 (
18
#192
08
#193
b00000000000000000000000001011010 (
18
#194
08
#195
b00000000000000000000000001011011 (
18
#196
08
#197
b00000000000000000000000001011100 (
18
#198
08
#199
b00000000000000000000000001011101 (
18
#200
08
1D
b01 a
#201
b00000000000000000000000001011110 (
17
18
#202
08
#203
b00000000000000000000000001011111 (
b01 -
07
18
0E
1G
b00 a
#204
08
0D
#205
b00000000000000000000000001100000 (
b00 -
18
1E
0G
#206
08
#207
b00000000000000000000000001100001 (
18
#208
08
#209
b00000000000000000000000001100010 (
18
#210
08
#211
b00000000000000000000000001100011 (
18
#212
08
#213
b00000000000000000000000001100100 (
18
#214
08
#215
b00000000000000000000000001100101 (
18
#216
08
